{
		"entityDerive":"buffItem",
		"basePropDesc":{
			"editor.ui.addScore":[
				100
			],
			"editor.ui.damage":[
				1
			],
			"editor.ui.addHp":[
				1
			]
		},
		"settingUI":{
			"tabList":[
				{
					"wndName":"BaseProp",
					"leftName":"editor.ui.baseProp"
				}
			]
		},
		"baseDesc":"flower_desc",
		"addHp":1,
		"viewDistance":32,
		"boundingVolume":{
			"type":"Box",
			"params":[
				0.99,
				1,
				0.99
			]
		},
		"hideHp":1,
		"avoidCliff":true,
		"editBaseFunc":"flower_edit",
		"meetCollisionBackRun":true,
		"showBoundBox":true,
		"damage":1,
		"canClick":false,
		"unassailable": 1,
		"undamageable": 1,
		"name":"",
		"canMove":true,
		"avoidCliffHight":15,
		"enableAI":false,
		"desc":"{flower_desc}\n{editor.ui.addScore}100\n{editor.ui.damage}1\n{editor.ui.addHp}1\n",
		"addSkill":"myplugin\/fire_ball",
		"disableShadow":true,
		"icon":"flower.png",
		"actorName":"object_flower.actor",
		"posSyncDelay":1,
		"moveSpeed":0.11,
		"collision":false,
		"gravity":0,
		"canjump":true,
		"boundBoxColor":[
			1,
			1,
			1,
			1
		],
		"addScore":100
	}