{
		"rotation":{
			"z":0,
			"x":180,
			"y":90
		},
		"editBaseFunc":"block_breakTime",
		"dropItemList":[
			[
				"block",
				1,
				1,
				"myplugin\/stone_brick_stairs07_down",
				"block:myplugin\/stone_brick_stairs07_down",
				"stone_brick_stairs07_down"
			]
		],
		"settingUI":{
			"tabList":[
				{
					"leftName":"editor.ui.baseProp",
					"wndName":"BaseProp"
				}
			]
		},
		"defaultTexture":"\/block\/stone_brick_stairs\/stone_brick.png",
		"base":"oak_stairs04"
	}