{
    "Dialog": {
        "Window": {
            "Type": "Layout",
            "Name": "rolePanelTabCell",
            "Property": [
                {
                    "Name": "Area",
                    "Value": "{{0,0},{0,100},{0,154},{0,186}}"
                },
                {
                    "Name": "WndOpenSound",
                    "Value": "0"
                },
                {
                    "Name": "WndCloseSound",
                    "Value": "0"
                }
            ],
            "Window": [
                {
                    "Type": "StaticImage",
                    "Name": "rolePanelTabCell-cellBg",
                    "Property": [
                        {
                            "Name": "Area",
                            "Value": "{{0,0},{0,-10},{1,0},{1,-1}}"
                        },
                        {
                            "Name": "WndOpenSound",
                            "Value": "0"
                        },
                        {
                            "Name": "WndCloseSound",
                            "Value": "0"
                        },
                        {
                            "Name": "StretchType",
                            "Value": "NineGrid"
                        },
                        {
                            "Name": "HexgonOverlayerColor",
                            "Value": "1 1 1 1"
                        },
                        {
                            "Name": "HexgonOverlayerImage",
                            "Value": ""
                        },
                        {
                            "Name": "HexgonSideColor",
                            "Value": "1 1 1 1"
                        },
                        {
                            "Name": "HexgonSideImage",
                            "Value": ""
                        },
                        {
                            "Name": "HexgonTopColor",
                            "Value": "1 1 1 1"
                        },
                        {
                            "Name": "HexgonTopImage",
                            "Value": ""
                        },
                        {
                            "Name": "ImageName",
                            "Value": "set:role_Panel.json image:but_tab_nor.png"
                        }
                    ],
                    "Window": [
                        {
                            "Type": "StaticText",
                            "Name": "rolePanelTabCell-tabText",
                            "Property": [
                                {
                                    "Name": "Area",
                                    "Value": "{{0,-7},{0,12},{0,123},{0,52}}"
                                },
                                {
                                    "Name": "HorizontalAlignment",
                                    "Value": "Right"
                                },
                                {
                                    "Name": "WndOpenSound",
                                    "Value": "0"
                                },
                                {
                                    "Name": "WndCloseSound",
                                    "Value": "0"
                                },
                                {
                                    "Name": "TextColor",
                                    "Value": "0.337255 0.34902 0.360784 1"
                                },
                                {
                                    "Name": "TextHorzAlignment",
                                    "Value": "Centre"
                                },
                                {
                                    "Name": "TextLineExtraSpace",
                                    "Value": "0"
                                },
                                {
                                    "Name": "TextVertAlignment",
                                    "Value": "Centre"
                                }
                            ]
                        }
                    ]
                },
                {
                    "Type": "StaticImage",
                    "Name": "rolePanelTabCell-selectImg",
                    "Property": [
                        {
                            "Name": "Area",
                            "Value": "{{0,-8},{0,-4},{0,122},{0,49}}"
                        },
                        {
                            "Name": "HorizontalAlignment",
                            "Value": "Right"
                        },
                        {
                            "Name": "WndOpenSound",
                            "Value": "0"
                        },
                        {
                            "Name": "WndCloseSound",
                            "Value": "0"
                        },
                        {
                            "Name": "HexgonOverlayerColor",
                            "Value": "1 1 1 1"
                        },
                        {
                            "Name": "HexgonOverlayerImage",
                            "Value": ""
                        },
                        {
                            "Name": "HexgonSideColor",
                            "Value": "1 1 1 1"
                        },
                        {
                            "Name": "HexgonSideImage",
                            "Value": ""
                        },
                        {
                            "Name": "HexgonTopColor",
                            "Value": "1 1 1 1"
                        },
                        {
                            "Name": "HexgonTopImage",
                            "Value": ""
                        },
                        {
                            "Name": "ImageName",
                            "Value": "set:role_Panel.json image:but_tab_selected.png"
                        }
                    ],
                    "Window": [
                        {
                            "Type": "StaticText",
                            "Name": "rolePanelTabCell-selectText",
                            "Property": [
                                {
                                    "Name": "Area",
                                    "Value": "{{0,0},{0,13},{0,114},{0,37}}"
                                },
                                {
                                    "Name": "HorizontalAlignment",
                                    "Value": "Centre"
                                },
                                {
                                    "Name": "WndOpenSound",
                                    "Value": "0"
                                },
                                {
                                    "Name": "WndCloseSound",
                                    "Value": "0"
                                },
                                {
                                    "Name": "TextHorzAlignment",
                                    "Value": "Centre"
                                },
                                {
                                    "Name": "TextLineExtraSpace",
                                    "Value": "0"
                                },
                                {
                                    "Name": "TextVertAlignment",
                                    "Value": "Bottom"
                                }
                            ]
                        }
                    ]
                },
                {
                    "Type": "Button",
                    "Name": "rolePanelTabCell-click",
                    "Property": [
                        {
                            "Name": "Area",
                            "Value": "{{0,-1},{0,1},{1,-1},{0.6,1}}"
                        },
                        {
                            "Name": "WndOpenSound",
                            "Value": "0"
                        },
                        {
                            "Name": "WndCloseSound",
                            "Value": "0"
                        },
                        {
                            "Name": "HexgonOverlayerColor",
                            "Value": "1 1 1 1"
                        },
                        {
                            "Name": "HexgonOverlayerImage",
                            "Value": ""
                        },
                        {
                            "Name": "HexgonSideColor",
                            "Value": "1 1 1 1"
                        },
                        {
                            "Name": "HexgonSideImage",
                            "Value": ""
                        },
                        {
                            "Name": "HexgonTopColor",
                            "Value": "1 1 1 1"
                        },
                        {
                            "Name": "HexgonTopImage",
                            "Value": ""
                        },
                        {
                            "Name": "SoundName",
                            "Value": "0"
                        },
                        {
                            "Name": "TextHorzAlignment",
                            "Value": "Centre"
                        },
                        {
                            "Name": "TextVertAlignment",
                            "Value": "Centre"
                        }
                    ]
                }
            ]
        }
    }
}