{
    "dropItemList": [
        [
            "block",
            1,
            1,
            "myplugin/leaves_big_oak",
            "block:myplugin/leaves_big_oak",
            "leaves_big_oak"
        ]
    ],
    "editBaseFunc": "block_breakTime",
    "breakTime": 20,
    "settingUI": {
        "tabList": [
            {
                "leftName": "editor.ui.baseProp",
                "wndName": "BaseProp"
            }
        ]
    },
    "isOpaqueFullCube": false,
    "texture": [
        "leaves_big_oak.png",
        "leaves_big_oak.png",
        "leaves_big_oak.png",
        "leaves_big_oak.png",
        "leaves_big_oak.png",
        "leaves_big_oak.png"
    ],
     
    "base": "base_block"
}